README.md
pretty_toml_sort/__init__.py
pretty_toml_sort/cli.py
pretty_toml_sort/py.typed
pretty_toml_sort/tomlsort.py
pretty_toml_sort-0.0.3.dist-info/LICENSE
pretty_toml_sort-0.0.3.dist-info/METADATA
pretty_toml_sort-0.0.3.dist-info/WHEEL
pretty_toml_sort-0.0.3.dist-info/entry_points.txt
pretty_toml_sort-0.0.3.dist-info/RECORD
