Metadata-Version: 2.1
Name: pretty-toml-sort
Version: 0.0.3
Summary: Toml sorting library
Home-page: https://github.com/brodybits/pretty-toml-sort
License: MIT
Keywords: toml,sort,cli,unix,utility
Author: Sam Roeca
Author-email: samuel.roeca@gmail.com
Requires-Python: >=3.7,<4.0
Classifier: Development Status :: 3 - Alpha
Classifier: Environment :: Console
Classifier: License :: OSI Approved :: MIT License
Classifier: Programming Language :: Python :: 3
Classifier: Programming Language :: Python :: 3.7
Classifier: Programming Language :: Python :: 3.8
Classifier: Programming Language :: Python :: 3.9
Classifier: Programming Language :: Python :: 3.10
Classifier: Programming Language :: Python :: 3.11
Classifier: Programming Language :: Python :: 3.12
Classifier: Topic :: Software Development :: Code Generators
Classifier: Topic :: Utilities
Classifier: Typing :: Typed
Requires-Dist: tomlkit (>=0.12.3)
Project-URL: Repository, https://github.com/brodybits/pretty-toml-sort
